{"entities":{"pages":{"Home":{"id":"Home","title":"Ktor Discord API","url":"home.html","level":0,"tabIndex":0},"k1us3y_3":{"id":"k1us3y_3","title":"Démarrer","level":0,"pages":["Introduction","Premiers_pas"],"tabIndex":1},"Introduction":{"id":"Introduction","title":"Introduction \u0026 installation","url":"introduction.html","level":1,"parentId":"k1us3y_3","tabIndex":0},"Premiers_pas":{"id":"Premiers_pas","title":"Premiers pas","url":"premiers-pas.html","level":1,"parentId":"k1us3y_3","tabIndex":1},"k1us3y_4":{"id":"k1us3y_4","title":"Le client","level":0,"pages":["Client","Connexion","Presence"],"tabIndex":2},"Client":{"id":"Client","title":"Créer \u0026 configurer le client","url":"client.html","level":1,"parentId":"k1us3y_4","tabIndex":0},"Connexion":{"id":"Connexion","title":"Se connecter à la Gateway","url":"connexion.html","level":1,"parentId":"k1us3y_4","tabIndex":1},"Presence":{"id":"Presence","title":"Présence \u0026 activité","url":"presence.html","level":1,"parentId":"k1us3y_4","tabIndex":2},"k1us3y_5":{"id":"k1us3y_5","title":"Interagir avec Discord","level":0,"pages":["Rest_overview","Rest_messages","Rest_channels","Rest_guilds","Rest_reactions","Rest_users"],"tabIndex":3},"Rest_overview":{"id":"Rest_overview","title":"Vue d\u0027ensemble \u0026 réponses","url":"rest-overview.html","level":1,"parentId":"k1us3y_5","tabIndex":0},"Rest_messages":{"id":"Rest_messages","title":"Messages","url":"rest-messages.html","level":1,"parentId":"k1us3y_5","tabIndex":1},"Rest_channels":{"id":"Rest_channels","title":"Salons","url":"rest-channels.html","level":1,"parentId":"k1us3y_5","tabIndex":2},"Rest_guilds":{"id":"Rest_guilds","title":"Serveurs, membres, rôles \u0026 bans","url":"rest-guilds.html","level":1,"parentId":"k1us3y_5","tabIndex":3},"Rest_reactions":{"id":"Rest_reactions","title":"Réactions \u0026 émojis","url":"rest-reactions.html","level":1,"parentId":"k1us3y_5","tabIndex":4},"Rest_users":{"id":"Rest_users","title":"Utilisateurs","url":"rest-users.html","level":1,"parentId":"k1us3y_5","tabIndex":5},"k1us3y_6":{"id":"k1us3y_6","title":"Événements","level":0,"pages":["Events","Events_catalog"],"tabIndex":4},"Events":{"id":"Events","title":"Réagir aux événements","url":"events.html","level":1,"parentId":"k1us3y_6","tabIndex":0},"Events_catalog":{"id":"Events_catalog","title":"Catalogue des événements","url":"events-catalog.html","level":1,"parentId":"k1us3y_6","tabIndex":1},"k1us3y_7":{"id":"k1us3y_7","title":"Interactions","level":0,"pages":["Commands","Components","Interaction_responses"],"tabIndex":5},"Commands":{"id":"Commands","title":"Commandes d\u0027application","url":"commands.html","level":1,"parentId":"k1us3y_7","tabIndex":0},"Components":{"id":"Components","title":"Composants \u0026 boutons","url":"components.html","level":1,"parentId":"k1us3y_7","tabIndex":1},"Interaction_responses":{"id":"Interaction_responses","title":"Réponses aux interactions","url":"interaction-responses.html","level":1,"parentId":"k1us3y_7","tabIndex":2},"k1us3y_8":{"id":"k1us3y_8","title":"Construire des messages","level":0,"pages":["Message_dsl","Message_dsl_embeds","Message_dsl_buttons"],"tabIndex":6},"Message_dsl":{"id":"Message_dsl","title":"Le DSL de message","url":"message-dsl.html","level":1,"parentId":"k1us3y_8","tabIndex":0},"Message_dsl_embeds":{"id":"Message_dsl_embeds","title":"Embeds","url":"message-dsl-embeds.html","level":1,"parentId":"k1us3y_8","tabIndex":1},"Message_dsl_buttons":{"id":"Message_dsl_buttons","title":"Boutons","url":"message-dsl-buttons.html","level":1,"parentId":"k1us3y_8","tabIndex":2},"k1us3y_9":{"id":"k1us3y_9","title":"Avancé","level":0,"pages":["Adv_architecture","Adv_serialization","Adv_gateway"],"tabIndex":7},"Adv_architecture":{"id":"Adv_architecture","title":"Architecture","url":"adv-architecture.html","level":1,"parentId":"k1us3y_9","tabIndex":0},"Adv_serialization":{"id":"Adv_serialization","title":"Sérialisation","url":"adv-serialization.html","level":1,"parentId":"k1us3y_9","tabIndex":1},"Adv_gateway":{"id":"Adv_gateway","title":"Cycle de vie de la Gateway","url":"adv-gateway.html","level":1,"parentId":"k1us3y_9","tabIndex":2}}},"topLevelIds":["Home","k1us3y_3","k1us3y_4","k1us3y_5","k1us3y_6","k1us3y_7","k1us3y_8","k1us3y_9"]}